openql/__init__.py
openql/conftest.py
openql/release.py
openql-0.0.1.dev1.dist-info/DESCRIPTION.rst
openql-0.0.1.dev1.dist-info/METADATA
openql-0.0.1.dev1.dist-info/RECORD
openql-0.0.1.dev1.dist-info/WHEEL
openql-0.0.1.dev1.dist-info/metadata.json
openql-0.0.1.dev1.dist-info/top_level.txt
