Metadata-Version: 2.0
Name: openql
Version: 0.0.1.dev1
Summary: OpenQL is the Quantum library in Python.
Home-page: http://openql.org
Author: OpenQL development team
Author-email: committer@openql.org
License: Apache 2.0
Keywords: Math Physics quantum
Platform: UNKNOWN
Classifier: License :: OSI Approved :: Apache Software License
Classifier: Operating System :: OS Independent
Classifier: Programming Language :: Python
Classifier: Topic :: Scientific/Engineering
Classifier: Topic :: Scientific/Engineering :: Mathematics
Classifier: Topic :: Scientific/Engineering :: Physics
Classifier: Programming Language :: Python :: 3.5
Classifier: Programming Language :: Python :: 3.6
